{"serialNumber":"urn:uuid:41c06f11-7f70-4bc6-b80c-9f189960940e","specVersion":"1.4","components":[{"type":"application","licenses":[{"license":{"name":"GPL-2.0-or-later"}},{"license":{"name":"GPL-2.0-only"}}],"version":"0.1.7","name":"einat-ebpf"},{"version":"24.354.13337~0fc7009","name":"luci-app-shadowsocks-rust","licenses":[{"license":{"name":"Apache-2.0"}}],"type":"application"},{"version":"24.354.13337~0fc7009","name":"luci-i18n-shadowsocks-rust-ar","type":"application","licenses":[{"license":{"name":"Apache-2.0"}}]},{"type":"application","licenses":[{"license":{"name":"Apache-2.0"}}],"name":"luci-i18n-shadowsocks-rust-bg","version":"24.354.13337~0fc7009"},{"version":"24.354.13337~0fc7009","name":"luci-i18n-shadowsocks-rust-bn","type":"application","licenses":[{"license":{"name":"Apache-2.0"}}]},{"name":"luci-i18n-shadowsocks-rust-ca","version":"24.354.13337~0fc7009","type":"application","licenses":[{"license":{"name":"Apache-2.0"}}]},{"name":"luci-i18n-shadowsocks-rust-cs","version":"24.354.13337~0fc7009","licenses":[{"license":{"name":"Apache-2.0"}}],"type":"application"},{"licenses":[{"license":{"name":"Apache-2.0"}}],"type":"application","version":"24.354.13337~0fc7009","name":"luci-i18n-shadowsocks-rust-da"},{"name":"luci-i18n-shadowsocks-rust-de","version":"24.354.13337~0fc7009","licenses":[{"license":{"name":"Apache-2.0"}}],"type":"application"},{"name":"luci-i18n-shadowsocks-rust-el","version":"24.354.13337~0fc7009","licenses":[{"license":{"name":"Apache-2.0"}}],"type":"application"},{"licenses":[{"license":{"name":"Apache-2.0"}}],"type":"application","version":"24.354.13337~0fc7009","name":"luci-i18n-shadowsocks-rust-es"},{"name":"luci-i18n-shadowsocks-rust-fi","version":"24.354.13337~0fc7009","licenses":[{"license":{"name":"Apache-2.0"}}],"type":"application"},{"type":"application","licenses":[{"license":{"name":"Apache-2.0"}}],"name":"luci-i18n-shadowsocks-rust-fr","version":"24.354.13337~0fc7009"},{"version":"24.354.13337~0fc7009","name":"luci-i18n-shadowsocks-rust-he","type":"application","licenses":[{"license":{"name":"Apache-2.0"}}]},{"licenses":[{"license":{"name":"Apache-2.0"}}],"type":"application","name":"luci-i18n-shadowsocks-rust-hi","version":"24.354.13337~0fc7009"},{"type":"application","licenses":[{"license":{"name":"Apache-2.0"}}],"name":"luci-i18n-shadowsocks-rust-hu","version":"24.354.13337~0fc7009"},{"name":"luci-i18n-shadowsocks-rust-it","version":"24.354.13337~0fc7009","licenses":[{"license":{"name":"Apache-2.0"}}],"type":"application"},{"name":"luci-i18n-shadowsocks-rust-ja","version":"24.354.13337~0fc7009","type":"application","licenses":[{"license":{"name":"Apache-2.0"}}]},{"version":"24.354.13337~0fc7009","name":"luci-i18n-shadowsocks-rust-ko","type":"application","licenses":[{"license":{"name":"Apache-2.0"}}]},{"name":"luci-i18n-shadowsocks-rust-lt","version":"24.354.13337~0fc7009","licenses":[{"license":{"name":"Apache-2.0"}}],"type":"application"},{"type":"application","licenses":[{"license":{"name":"Apache-2.0"}}],"version":"24.354.13337~0fc7009","name":"luci-i18n-shadowsocks-rust-mr"},{"name":"luci-i18n-shadowsocks-rust-ms","version":"24.354.13337~0fc7009","type":"application","licenses":[{"license":{"name":"Apache-2.0"}}]},{"licenses":[{"license":{"name":"Apache-2.0"}}],"type":"application","version":"24.354.13337~0fc7009","name":"luci-i18n-shadowsocks-rust-nl"},{"version":"24.354.13337~0fc7009","name":"luci-i18n-shadowsocks-rust-no","licenses":[{"license":{"name":"Apache-2.0"}}],"type":"application"},{"version":"24.354.13337~0fc7009","name":"luci-i18n-shadowsocks-rust-pl","licenses":[{"license":{"name":"Apache-2.0"}}],"type":"application"},{"name":"luci-i18n-shadowsocks-rust-pt","version":"24.354.13337~0fc7009","type":"application","licenses":[{"license":{"name":"Apache-2.0"}}]},{"name":"luci-i18n-shadowsocks-rust-pt-br","version":"24.354.13337~0fc7009","licenses":[{"license":{"name":"Apache-2.0"}}],"type":"application"},{"version":"24.354.13337~0fc7009","name":"luci-i18n-shadowsocks-rust-ro","licenses":[{"license":{"name":"Apache-2.0"}}],"type":"application"},{"type":"application","licenses":[{"license":{"name":"Apache-2.0"}}],"version":"24.354.13337~0fc7009","name":"luci-i18n-shadowsocks-rust-ru"},{"type":"application","licenses":[{"license":{"name":"Apache-2.0"}}],"version":"24.354.13337~0fc7009","name":"luci-i18n-shadowsocks-rust-sk"},{"name":"luci-i18n-shadowsocks-rust-sv","version":"24.354.13337~0fc7009","licenses":[{"license":{"name":"Apache-2.0"}}],"type":"application"},{"version":"24.354.13337~0fc7009","name":"luci-i18n-shadowsocks-rust-tr","licenses":[{"license":{"name":"Apache-2.0"}}],"type":"application"},{"type":"application","licenses":[{"license":{"name":"Apache-2.0"}}],"name":"luci-i18n-shadowsocks-rust-uk","version":"24.354.13337~0fc7009"},{"version":"24.354.13337~0fc7009","name":"luci-i18n-shadowsocks-rust-vi","licenses":[{"license":{"name":"Apache-2.0"}}],"type":"application"},{"type":"application","licenses":[{"license":{"name":"Apache-2.0"}}],"version":"24.354.13337~0fc7009","name":"luci-i18n-shadowsocks-rust-zh-cn"},{"licenses":[{"license":{"name":"Apache-2.0"}}],"type":"application","version":"24.354.13337~0fc7009","name":"luci-i18n-shadowsocks-rust-zh-tw"},{"type":"application","licenses":[{"license":{"name":"MIT"}}],"name":"shadowsocks-rust-config","version":"1.22.0"},{"licenses":[{"license":{"name":"MIT"}}],"type":"application","name":"shadowsocks-rust-sslocal","version":"1.22.0"},{"version":"1.22.0","name":"shadowsocks-rust-ssmanager","type":"application","licenses":[{"license":{"name":"MIT"}}]},{"licenses":[{"license":{"name":"MIT"}}],"type":"application","name":"shadowsocks-rust-ssserver","version":"1.22.0"},{"licenses":[{"license":{"name":"MIT"}}],"type":"application","version":"1.22.0","name":"shadowsocks-rust-ssservice"},{"type":"application","licenses":[{"license":{"name":"MIT"}}],"version":"1.22.0","name":"shadowsocks-rust-ssurl"}],"bomFormat":"CycloneDX","version":1,"metadata":{"timestamp":"2025-03-16T10:42:33Z"}}