{"bomFormat":"CycloneDX","components":[{"licenses":[{"license":{"name":"GPL-2.0-or-later"}},{"license":{"name":"GPL-2.0-only"}}],"type":"application","version":"0.1.5","name":"einat-ebpf"},{"name":"luci-app-shadowsocks-rust","licenses":[{"license":{"name":"Apache-2.0"}}],"version":"24.345.29432~611d2f9","type":"application"},{"name":"luci-i18n-shadowsocks-rust-ar","licenses":[{"license":{"name":"Apache-2.0"}}],"type":"application","version":"24.345.29432~611d2f9"},{"name":"luci-i18n-shadowsocks-rust-bg","type":"application","version":"24.345.29432~611d2f9","licenses":[{"license":{"name":"Apache-2.0"}}]},{"name":"luci-i18n-shadowsocks-rust-bn","licenses":[{"license":{"name":"Apache-2.0"}}],"type":"application","version":"24.345.29432~611d2f9"},{"licenses":[{"license":{"name":"Apache-2.0"}}],"version":"24.345.29432~611d2f9","type":"application","name":"luci-i18n-shadowsocks-rust-ca"},{"name":"luci-i18n-shadowsocks-rust-cs","version":"24.345.29432~611d2f9","type":"application","licenses":[{"license":{"name":"Apache-2.0"}}]},{"name":"luci-i18n-shadowsocks-rust-da","type":"application","version":"24.345.29432~611d2f9","licenses":[{"license":{"name":"Apache-2.0"}}]},{"name":"luci-i18n-shadowsocks-rust-de","licenses":[{"license":{"name":"Apache-2.0"}}],"type":"application","version":"24.345.29432~611d2f9"},{"name":"luci-i18n-shadowsocks-rust-el","licenses":[{"license":{"name":"Apache-2.0"}}],"type":"application","version":"24.345.29432~611d2f9"},{"version":"24.345.29432~611d2f9","type":"application","licenses":[{"license":{"name":"Apache-2.0"}}],"name":"luci-i18n-shadowsocks-rust-es"},{"version":"24.345.29432~611d2f9","type":"application","licenses":[{"license":{"name":"Apache-2.0"}}],"name":"luci-i18n-shadowsocks-rust-fi"},{"licenses":[{"license":{"name":"Apache-2.0"}}],"type":"application","version":"24.345.29432~611d2f9","name":"luci-i18n-shadowsocks-rust-fr"},{"licenses":[{"license":{"name":"Apache-2.0"}}],"version":"24.345.29432~611d2f9","type":"application","name":"luci-i18n-shadowsocks-rust-he"},{"licenses":[{"license":{"name":"Apache-2.0"}}],"type":"application","version":"24.345.29432~611d2f9","name":"luci-i18n-shadowsocks-rust-hi"},{"name":"luci-i18n-shadowsocks-rust-hu","type":"application","version":"24.345.29432~611d2f9","licenses":[{"license":{"name":"Apache-2.0"}}]},{"name":"luci-i18n-shadowsocks-rust-it","licenses":[{"license":{"name":"Apache-2.0"}}],"version":"24.345.29432~611d2f9","type":"application"},{"name":"luci-i18n-shadowsocks-rust-ja","type":"application","version":"24.345.29432~611d2f9","licenses":[{"license":{"name":"Apache-2.0"}}]},{"version":"24.345.29432~611d2f9","type":"application","licenses":[{"license":{"name":"Apache-2.0"}}],"name":"luci-i18n-shadowsocks-rust-ko"},{"name":"luci-i18n-shadowsocks-rust-lt","licenses":[{"license":{"name":"Apache-2.0"}}],"version":"24.345.29432~611d2f9","type":"application"},{"type":"application","version":"24.345.29432~611d2f9","licenses":[{"license":{"name":"Apache-2.0"}}],"name":"luci-i18n-shadowsocks-rust-mr"},{"licenses":[{"license":{"name":"Apache-2.0"}}],"version":"24.345.29432~611d2f9","type":"application","name":"luci-i18n-shadowsocks-rust-ms"},{"name":"luci-i18n-shadowsocks-rust-nl","type":"application","version":"24.345.29432~611d2f9","licenses":[{"license":{"name":"Apache-2.0"}}]},{"licenses":[{"license":{"name":"Apache-2.0"}}],"type":"application","version":"24.345.29432~611d2f9","name":"luci-i18n-shadowsocks-rust-no"},{"licenses":[{"license":{"name":"Apache-2.0"}}],"type":"application","version":"24.345.29432~611d2f9","name":"luci-i18n-shadowsocks-rust-pl"},{"name":"luci-i18n-shadowsocks-rust-pt","version":"24.345.29432~611d2f9","type":"application","licenses":[{"license":{"name":"Apache-2.0"}}]},{"version":"24.345.29432~611d2f9","type":"application","licenses":[{"license":{"name":"Apache-2.0"}}],"name":"luci-i18n-shadowsocks-rust-pt-br"},{"name":"luci-i18n-shadowsocks-rust-ro","licenses":[{"license":{"name":"Apache-2.0"}}],"version":"24.345.29432~611d2f9","type":"application"},{"licenses":[{"license":{"name":"Apache-2.0"}}],"type":"application","version":"24.345.29432~611d2f9","name":"luci-i18n-shadowsocks-rust-ru"},{"name":"luci-i18n-shadowsocks-rust-sk","licenses":[{"license":{"name":"Apache-2.0"}}],"type":"application","version":"24.345.29432~611d2f9"},{"name":"luci-i18n-shadowsocks-rust-sv","version":"24.345.29432~611d2f9","type":"application","licenses":[{"license":{"name":"Apache-2.0"}}]},{"name":"luci-i18n-shadowsocks-rust-tr","type":"application","version":"24.345.29432~611d2f9","licenses":[{"license":{"name":"Apache-2.0"}}]},{"name":"luci-i18n-shadowsocks-rust-uk","licenses":[{"license":{"name":"Apache-2.0"}}],"type":"application","version":"24.345.29432~611d2f9"},{"name":"luci-i18n-shadowsocks-rust-vi","type":"application","version":"24.345.29432~611d2f9","licenses":[{"license":{"name":"Apache-2.0"}}]},{"name":"luci-i18n-shadowsocks-rust-zh-cn","type":"application","version":"24.345.29432~611d2f9","licenses":[{"license":{"name":"Apache-2.0"}}]},{"name":"luci-i18n-shadowsocks-rust-zh-tw","licenses":[{"license":{"name":"Apache-2.0"}}],"type":"application","version":"24.345.29432~611d2f9"},{"version":"1.21.2","type":"application","licenses":[{"license":{"name":"MIT"}}],"name":"shadowsocks-rust-config"},{"name":"shadowsocks-rust-sslocal","licenses":[{"license":{"name":"MIT"}}],"type":"application","version":"1.21.2"},{"name":"shadowsocks-rust-ssmanager","licenses":[{"license":{"name":"MIT"}}],"version":"1.21.2","type":"application"},{"name":"shadowsocks-rust-ssserver","licenses":[{"license":{"name":"MIT"}}],"type":"application","version":"1.21.2"},{"version":"1.21.2","type":"application","licenses":[{"license":{"name":"MIT"}}],"name":"shadowsocks-rust-ssservice"},{"name":"shadowsocks-rust-ssurl","licenses":[{"license":{"name":"MIT"}}],"type":"application","version":"1.21.2"}],"serialNumber":"urn:uuid:26819e2e-1d14-465b-a207-61f706c0b073","version":1,"specVersion":"1.4","metadata":{"timestamp":"2024-12-12T03:31:42Z"}}