{"metadata":{"timestamp":"2025-03-22T20:15:27Z"},"version":1,"bomFormat":"CycloneDX","components":[{"version":"0.1.7","name":"einat-ebpf","type":"application","licenses":[{"license":{"name":"GPL-2.0-or-later"}},{"license":{"name":"GPL-2.0-only"}}]},{"licenses":[{"license":{"name":"Apache-2.0"}}],"type":"application","name":"luci-app-shadowsocks-rust","version":"24.354.13337~0fc7009"},{"name":"luci-i18n-shadowsocks-rust-ar","version":"24.354.13337~0fc7009","licenses":[{"license":{"name":"Apache-2.0"}}],"type":"application"},{"licenses":[{"license":{"name":"Apache-2.0"}}],"type":"application","name":"luci-i18n-shadowsocks-rust-bg","version":"24.354.13337~0fc7009"},{"version":"24.354.13337~0fc7009","name":"luci-i18n-shadowsocks-rust-bn","type":"application","licenses":[{"license":{"name":"Apache-2.0"}}]},{"version":"24.354.13337~0fc7009","name":"luci-i18n-shadowsocks-rust-ca","type":"application","licenses":[{"license":{"name":"Apache-2.0"}}]},{"name":"luci-i18n-shadowsocks-rust-cs","version":"24.354.13337~0fc7009","licenses":[{"license":{"name":"Apache-2.0"}}],"type":"application"},{"type":"application","licenses":[{"license":{"name":"Apache-2.0"}}],"version":"24.354.13337~0fc7009","name":"luci-i18n-shadowsocks-rust-da"},{"name":"luci-i18n-shadowsocks-rust-de","version":"24.354.13337~0fc7009","licenses":[{"license":{"name":"Apache-2.0"}}],"type":"application"},{"type":"application","licenses":[{"license":{"name":"Apache-2.0"}}],"version":"24.354.13337~0fc7009","name":"luci-i18n-shadowsocks-rust-el"},{"name":"luci-i18n-shadowsocks-rust-es","version":"24.354.13337~0fc7009","licenses":[{"license":{"name":"Apache-2.0"}}],"type":"application"},{"name":"luci-i18n-shadowsocks-rust-fi","version":"24.354.13337~0fc7009","licenses":[{"license":{"name":"Apache-2.0"}}],"type":"application"},{"version":"24.354.13337~0fc7009","name":"luci-i18n-shadowsocks-rust-fr","type":"application","licenses":[{"license":{"name":"Apache-2.0"}}]},{"name":"luci-i18n-shadowsocks-rust-he","version":"24.354.13337~0fc7009","licenses":[{"license":{"name":"Apache-2.0"}}],"type":"application"},{"name":"luci-i18n-shadowsocks-rust-hi","version":"24.354.13337~0fc7009","licenses":[{"license":{"name":"Apache-2.0"}}],"type":"application"},{"name":"luci-i18n-shadowsocks-rust-hu","version":"24.354.13337~0fc7009","licenses":[{"license":{"name":"Apache-2.0"}}],"type":"application"},{"licenses":[{"license":{"name":"Apache-2.0"}}],"type":"application","name":"luci-i18n-shadowsocks-rust-it","version":"24.354.13337~0fc7009"},{"name":"luci-i18n-shadowsocks-rust-ja","version":"24.354.13337~0fc7009","licenses":[{"license":{"name":"Apache-2.0"}}],"type":"application"},{"type":"application","licenses":[{"license":{"name":"Apache-2.0"}}],"version":"24.354.13337~0fc7009","name":"luci-i18n-shadowsocks-rust-ko"},{"name":"luci-i18n-shadowsocks-rust-lt","version":"24.354.13337~0fc7009","licenses":[{"license":{"name":"Apache-2.0"}}],"type":"application"},{"name":"luci-i18n-shadowsocks-rust-mr","version":"24.354.13337~0fc7009","licenses":[{"license":{"name":"Apache-2.0"}}],"type":"application"},{"version":"24.354.13337~0fc7009","name":"luci-i18n-shadowsocks-rust-ms","type":"application","licenses":[{"license":{"name":"Apache-2.0"}}]},{"name":"luci-i18n-shadowsocks-rust-nl","version":"24.354.13337~0fc7009","licenses":[{"license":{"name":"Apache-2.0"}}],"type":"application"},{"type":"application","licenses":[{"license":{"name":"Apache-2.0"}}],"version":"24.354.13337~0fc7009","name":"luci-i18n-shadowsocks-rust-no"},{"version":"24.354.13337~0fc7009","name":"luci-i18n-shadowsocks-rust-pl","type":"application","licenses":[{"license":{"name":"Apache-2.0"}}]},{"name":"luci-i18n-shadowsocks-rust-pt","version":"24.354.13337~0fc7009","licenses":[{"license":{"name":"Apache-2.0"}}],"type":"application"},{"name":"luci-i18n-shadowsocks-rust-pt-br","version":"24.354.13337~0fc7009","licenses":[{"license":{"name":"Apache-2.0"}}],"type":"application"},{"type":"application","licenses":[{"license":{"name":"Apache-2.0"}}],"version":"24.354.13337~0fc7009","name":"luci-i18n-shadowsocks-rust-ro"},{"licenses":[{"license":{"name":"Apache-2.0"}}],"type":"application","name":"luci-i18n-shadowsocks-rust-ru","version":"24.354.13337~0fc7009"},{"name":"luci-i18n-shadowsocks-rust-sk","version":"24.354.13337~0fc7009","licenses":[{"license":{"name":"Apache-2.0"}}],"type":"application"},{"version":"24.354.13337~0fc7009","name":"luci-i18n-shadowsocks-rust-sv","type":"application","licenses":[{"license":{"name":"Apache-2.0"}}]},{"type":"application","licenses":[{"license":{"name":"Apache-2.0"}}],"version":"24.354.13337~0fc7009","name":"luci-i18n-shadowsocks-rust-tr"},{"name":"luci-i18n-shadowsocks-rust-uk","version":"24.354.13337~0fc7009","licenses":[{"license":{"name":"Apache-2.0"}}],"type":"application"},{"version":"24.354.13337~0fc7009","name":"luci-i18n-shadowsocks-rust-vi","type":"application","licenses":[{"license":{"name":"Apache-2.0"}}]},{"type":"application","licenses":[{"license":{"name":"Apache-2.0"}}],"version":"24.354.13337~0fc7009","name":"luci-i18n-shadowsocks-rust-zh-cn"},{"type":"application","licenses":[{"license":{"name":"Apache-2.0"}}],"version":"24.354.13337~0fc7009","name":"luci-i18n-shadowsocks-rust-zh-tw"},{"licenses":[{"license":{"name":"MIT"}}],"type":"application","name":"shadowsocks-rust-config","version":"1.22.0"},{"type":"application","licenses":[{"license":{"name":"MIT"}}],"version":"1.22.0","name":"shadowsocks-rust-sslocal"},{"type":"application","licenses":[{"license":{"name":"MIT"}}],"version":"1.22.0","name":"shadowsocks-rust-ssmanager"},{"version":"1.22.0","name":"shadowsocks-rust-ssserver","type":"application","licenses":[{"license":{"name":"MIT"}}]},{"type":"application","licenses":[{"license":{"name":"MIT"}}],"version":"1.22.0","name":"shadowsocks-rust-ssservice"},{"type":"application","licenses":[{"license":{"name":"MIT"}}],"version":"1.22.0","name":"shadowsocks-rust-ssurl"}],"serialNumber":"urn:uuid:d268e68b-24e0-4656-beac-2cb22c2da224","specVersion":"1.4"}