{"specVersion":"1.4","bomFormat":"CycloneDX","version":1,"metadata":{"timestamp":"2025-03-21T14:42:09Z"},"components":[{"name":"alwaysonline","version":"1.2.1~206292ca","type":"application","licenses":[{"license":{"name":"MIT"}}]},{"version":"20240427","name":"fantastic-keyring","licenses":[{"license":{"name":"MIT"}}],"type":"application"},{"version":"20241201","name":"fantastic-packages-feeds","licenses":[{"license":{"name":"MIT"}}],"type":"application"},{"version":"2.38.0","name":"fastfetch","type":"application","licenses":[{"license":{"name":"MIT"}}]},{"type":"application","licenses":[{"license":{"name":"Apache-2.0"}}],"name":"go-stun","version":"0.1.4~d32c135f"},{"type":"application","version":"1.4.3","name":"internet-detector"},{"name":"internet-detector-mod-email","version":"1.4.3","type":"application"},{"name":"internet-detector-mod-modem-restart","version":"1.4.3","type":"application"},{"type":"library","version":"6.8.2","name":"libQt6Concurrent"},{"type":"library","version":"6.8.2","name":"libQt6Core"},{"version":"6.8.2","name":"libQt6DBus","type":"library"},{"type":"library","name":"libQt6Gui","version":"6.8.2"},{"type":"library","version":"6.8.2","name":"libQt6Network"},{"name":"libQt6PrintSupport","version":"6.8.2","type":"library"},{"type":"library","version":"6.8.2","name":"libQt6Sql"},{"version":"6.8.2","name":"libQt6Test","type":"library"},{"type":"library","name":"libQt6Widgets","version":"6.8.2"},{"type":"library","version":"6.8.2","name":"libQt6Xml"},{"name":"mihomo","version":"1.19.3","type":"application","licenses":[{"license":{"name":"GPL-2.0"}}]},{"name":"natmapt","version":"20250318","licenses":[{"license":{"name":"MIT"}}],"type":"application"},{"name":"natmapt-client-script-deluge","version":"0.2025.2.19","licenses":[{"license":{"name":"MIT"}}],"type":"application"},{"version":"0.2025.2.19","name":"natmapt-client-script-transmission","licenses":[{"license":{"name":"MIT"}}],"type":"application"},{"version":"0.2025.2.19","name":"natmapt-notify-script-pushbullet","licenses":[{"license":{"name":"MIT"}}],"type":"application"},{"version":"0.2025.2.19","name":"natmapt-notify-script-pushover","licenses":[{"license":{"name":"MIT"}}],"type":"application"},{"licenses":[{"license":{"name":"MIT"}}],"type":"application","version":"0.2025.2.19","name":"natmapt-notify-script-telegram"},{"type":"application","licenses":[{"license":{"name":"GPL-3.0-or-later"}}],"cpe":"cpe:/a:my-netdata:netdata:1.33.1","name":"netdata-ssl","version":"1.33.1"},{"licenses":[{"license":{"name":"GPL-2.0"}}],"type":"application","name":"pcap-dnsproxy","version":"0.4.9.13~70a40bb3"},{"name":"php-nginx","version":"0.2023.04.26","licenses":[{"license":{"name":"MIT"}}],"type":"application"},{"licenses":[{"license":{"name":"MIT"}}],"type":"application","version":"20231028","name":"plain-nginx"},{"version":"5.0.4","name":"qbittorrent","cpe":"cpe:/a:qbittorrent:qbittorrent:5.0.4","licenses":[{"license":{"name":"GPL-2.0+"}}],"type":"application"},{"name":"qt6-plugin-libqcertonlybackend","version":"6.8.2","type":"library"},{"type":"library","name":"qt6-plugin-libqminimal","version":"6.8.2"},{"type":"library","name":"qt6-plugin-libqnetworkmanager","version":"6.8.2"},{"name":"qt6-plugin-libqoffscreen","version":"6.8.2","type":"library"},{"name":"qt6-plugin-libqopensslbackend","version":"6.8.2","type":"library"},{"type":"library","name":"qt6-plugin-libqsqlite","version":"6.8.2"},{"type":"library","version":"6.8.2","name":"qt6-plugin-libqtuiotouchplugin"},{"type":"library","name":"qt6-plugin-libqxdgdesktopportal","version":"6.8.2"},{"version":"2.0.11","name":"rblibtorrent2.0","type":"library","licenses":[{"license":{"name":"BSD"}}]},{"type":"application","licenses":[{"license":{"name":"MIT"}}],"version":"1.5.1","name":"rgmac"},{"version":"1.7.10","name":"speedtest-go","type":"application","licenses":[{"license":{"name":"MIT"}}]},{"version":"1.2.17~cc5b875b","name":"stuntman-client","licenses":[{"license":{"name":"Apache-2.0"}}],"type":"application"},{"licenses":[{"license":{"name":"Apache-2.0"}}],"type":"application","version":"1.2.17~cc5b875b","name":"stuntman-server"},{"version":"1.2.17~cc5b875b","name":"stuntman-testcode","type":"application","licenses":[{"license":{"name":"Apache-2.0"}}]},{"version":"0.4.0.2~631954ea","name":"Toolkit","type":"application","licenses":[{"license":{"name":"GPL-2.0"}}]},{"version":"0.2025.01.25","name":"uci-alwaysonline","type":"application","licenses":[{"license":{"name":"MIT"}}]}],"serialNumber":"urn:uuid:9c36ebdb-196e-4150-b0b7-ace6d2507c22"}