{"components":[{"type":"application","name":"einat-ebpf","licenses":[{"license":{"name":"GPL-2.0-or-later"}},{"license":{"name":"GPL-2.0-only"}}],"version":"0.1.2"},{"version":"git-24.236.54363-d7cdf6a","licenses":[{"license":{"name":"Apache-2.0"}}],"type":"application","name":"luci-app-shadowsocks-rust"},{"type":"application","name":"luci-i18n-shadowsocks-rust-ar","version":"git-24.236.54363-d7cdf6a","licenses":[{"license":{"name":"Apache-2.0"}}]},{"type":"application","name":"luci-i18n-shadowsocks-rust-bg","version":"git-24.236.54363-d7cdf6a","licenses":[{"license":{"name":"Apache-2.0"}}]},{"version":"git-24.236.54363-d7cdf6a","licenses":[{"license":{"name":"Apache-2.0"}}],"name":"luci-i18n-shadowsocks-rust-bn","type":"application"},{"version":"git-24.236.54363-d7cdf6a","licenses":[{"license":{"name":"Apache-2.0"}}],"name":"luci-i18n-shadowsocks-rust-ca","type":"application"},{"type":"application","name":"luci-i18n-shadowsocks-rust-cs","licenses":[{"license":{"name":"Apache-2.0"}}],"version":"git-24.236.54363-d7cdf6a"},{"version":"git-24.236.54363-d7cdf6a","licenses":[{"license":{"name":"Apache-2.0"}}],"type":"application","name":"luci-i18n-shadowsocks-rust-da"},{"licenses":[{"license":{"name":"Apache-2.0"}}],"version":"git-24.236.54363-d7cdf6a","type":"application","name":"luci-i18n-shadowsocks-rust-de"},{"name":"luci-i18n-shadowsocks-rust-el","type":"application","licenses":[{"license":{"name":"Apache-2.0"}}],"version":"git-24.236.54363-d7cdf6a"},{"licenses":[{"license":{"name":"Apache-2.0"}}],"version":"git-24.236.54363-d7cdf6a","name":"luci-i18n-shadowsocks-rust-es","type":"application"},{"version":"git-24.236.54363-d7cdf6a","licenses":[{"license":{"name":"Apache-2.0"}}],"name":"luci-i18n-shadowsocks-rust-fi","type":"application"},{"type":"application","name":"luci-i18n-shadowsocks-rust-fr","licenses":[{"license":{"name":"Apache-2.0"}}],"version":"git-24.236.54363-d7cdf6a"},{"type":"application","name":"luci-i18n-shadowsocks-rust-he","version":"git-24.236.54363-d7cdf6a","licenses":[{"license":{"name":"Apache-2.0"}}]},{"type":"application","name":"luci-i18n-shadowsocks-rust-hi","licenses":[{"license":{"name":"Apache-2.0"}}],"version":"git-24.236.54363-d7cdf6a"},{"version":"git-24.236.54363-d7cdf6a","licenses":[{"license":{"name":"Apache-2.0"}}],"type":"application","name":"luci-i18n-shadowsocks-rust-hu"},{"licenses":[{"license":{"name":"Apache-2.0"}}],"version":"git-24.236.54363-d7cdf6a","name":"luci-i18n-shadowsocks-rust-it","type":"application"},{"name":"luci-i18n-shadowsocks-rust-ja","type":"application","licenses":[{"license":{"name":"Apache-2.0"}}],"version":"git-24.236.54363-d7cdf6a"},{"version":"git-24.236.54363-d7cdf6a","licenses":[{"license":{"name":"Apache-2.0"}}],"name":"luci-i18n-shadowsocks-rust-ko","type":"application"},{"type":"application","name":"luci-i18n-shadowsocks-rust-lt","licenses":[{"license":{"name":"Apache-2.0"}}],"version":"git-24.236.54363-d7cdf6a"},{"type":"application","name":"luci-i18n-shadowsocks-rust-mr","licenses":[{"license":{"name":"Apache-2.0"}}],"version":"git-24.236.54363-d7cdf6a"},{"type":"application","name":"luci-i18n-shadowsocks-rust-ms","licenses":[{"license":{"name":"Apache-2.0"}}],"version":"git-24.236.54363-d7cdf6a"},{"licenses":[{"license":{"name":"Apache-2.0"}}],"version":"git-24.236.54363-d7cdf6a","name":"luci-i18n-shadowsocks-rust-nl","type":"application"},{"type":"application","name":"luci-i18n-shadowsocks-rust-no","licenses":[{"license":{"name":"Apache-2.0"}}],"version":"git-24.236.54363-d7cdf6a"},{"name":"luci-i18n-shadowsocks-rust-pl","type":"application","version":"git-24.236.54363-d7cdf6a","licenses":[{"license":{"name":"Apache-2.0"}}]},{"type":"application","name":"luci-i18n-shadowsocks-rust-pt","version":"git-24.236.54363-d7cdf6a","licenses":[{"license":{"name":"Apache-2.0"}}]},{"licenses":[{"license":{"name":"Apache-2.0"}}],"version":"git-24.236.54363-d7cdf6a","type":"application","name":"luci-i18n-shadowsocks-rust-pt-br"},{"name":"luci-i18n-shadowsocks-rust-ro","type":"application","version":"git-24.236.54363-d7cdf6a","licenses":[{"license":{"name":"Apache-2.0"}}]},{"type":"application","name":"luci-i18n-shadowsocks-rust-ru","licenses":[{"license":{"name":"Apache-2.0"}}],"version":"git-24.236.54363-d7cdf6a"},{"type":"application","name":"luci-i18n-shadowsocks-rust-sk","version":"git-24.236.54363-d7cdf6a","licenses":[{"license":{"name":"Apache-2.0"}}]},{"licenses":[{"license":{"name":"Apache-2.0"}}],"version":"git-24.236.54363-d7cdf6a","name":"luci-i18n-shadowsocks-rust-sv","type":"application"},{"type":"application","name":"luci-i18n-shadowsocks-rust-tr","licenses":[{"license":{"name":"Apache-2.0"}}],"version":"git-24.236.54363-d7cdf6a"},{"version":"git-24.236.54363-d7cdf6a","licenses":[{"license":{"name":"Apache-2.0"}}],"name":"luci-i18n-shadowsocks-rust-uk","type":"application"},{"name":"luci-i18n-shadowsocks-rust-vi","type":"application","version":"git-24.236.54363-d7cdf6a","licenses":[{"license":{"name":"Apache-2.0"}}]},{"name":"luci-i18n-shadowsocks-rust-zh-cn","type":"application","licenses":[{"license":{"name":"Apache-2.0"}}],"version":"git-24.236.54363-d7cdf6a"},{"licenses":[{"license":{"name":"Apache-2.0"}}],"version":"git-24.236.54363-d7cdf6a","name":"luci-i18n-shadowsocks-rust-zh-tw","type":"application"},{"type":"application","name":"shadowsocks-rust-config","licenses":[{"license":{"name":"MIT"}}],"version":"1.21.0"},{"licenses":[{"license":{"name":"MIT"}}],"version":"1.21.0","type":"application","name":"shadowsocks-rust-sslocal"},{"version":"1.21.0","licenses":[{"license":{"name":"MIT"}}],"type":"application","name":"shadowsocks-rust-ssmanager"},{"type":"application","name":"shadowsocks-rust-ssserver","version":"1.21.0","licenses":[{"license":{"name":"MIT"}}]},{"version":"1.21.0","licenses":[{"license":{"name":"MIT"}}],"name":"shadowsocks-rust-ssservice","type":"application"},{"type":"application","name":"shadowsocks-rust-ssurl","version":"1.21.0","licenses":[{"license":{"name":"MIT"}}]}],"serialNumber":"urn:uuid:4c226430-9710-4816-b550-32c488f9253a","metadata":{"timestamp":"2024-10-12T19:43:42Z"},"version":1,"specVersion":"1.4","bomFormat":"CycloneDX"}