{"specVersion":"1.4","components":[{"licenses":[{"license":{"name":"GPL-2.0-or-later"}},{"license":{"name":"GPL-2.0-only"}}],"type":"application","version":"0.1.7","name":"einat-ebpf"},{"name":"luci-app-shadowsocks-rust","version":"git-24.236.54363-d7cdf6a","type":"application","licenses":[{"license":{"name":"Apache-2.0"}}]},{"type":"application","licenses":[{"license":{"name":"Apache-2.0"}}],"name":"luci-i18n-shadowsocks-rust-ar","version":"git-24.236.54363-d7cdf6a"},{"licenses":[{"license":{"name":"Apache-2.0"}}],"type":"application","version":"git-24.236.54363-d7cdf6a","name":"luci-i18n-shadowsocks-rust-bg"},{"type":"application","licenses":[{"license":{"name":"Apache-2.0"}}],"name":"luci-i18n-shadowsocks-rust-bn","version":"git-24.236.54363-d7cdf6a"},{"version":"git-24.236.54363-d7cdf6a","name":"luci-i18n-shadowsocks-rust-ca","licenses":[{"license":{"name":"Apache-2.0"}}],"type":"application"},{"type":"application","licenses":[{"license":{"name":"Apache-2.0"}}],"name":"luci-i18n-shadowsocks-rust-cs","version":"git-24.236.54363-d7cdf6a"},{"licenses":[{"license":{"name":"Apache-2.0"}}],"type":"application","version":"git-24.236.54363-d7cdf6a","name":"luci-i18n-shadowsocks-rust-da"},{"version":"git-24.236.54363-d7cdf6a","name":"luci-i18n-shadowsocks-rust-de","licenses":[{"license":{"name":"Apache-2.0"}}],"type":"application"},{"type":"application","licenses":[{"license":{"name":"Apache-2.0"}}],"name":"luci-i18n-shadowsocks-rust-el","version":"git-24.236.54363-d7cdf6a"},{"name":"luci-i18n-shadowsocks-rust-es","version":"git-24.236.54363-d7cdf6a","type":"application","licenses":[{"license":{"name":"Apache-2.0"}}]},{"name":"luci-i18n-shadowsocks-rust-fi","version":"git-24.236.54363-d7cdf6a","type":"application","licenses":[{"license":{"name":"Apache-2.0"}}]},{"version":"git-24.236.54363-d7cdf6a","name":"luci-i18n-shadowsocks-rust-fr","licenses":[{"license":{"name":"Apache-2.0"}}],"type":"application"},{"licenses":[{"license":{"name":"Apache-2.0"}}],"type":"application","version":"git-24.236.54363-d7cdf6a","name":"luci-i18n-shadowsocks-rust-he"},{"version":"git-24.236.54363-d7cdf6a","name":"luci-i18n-shadowsocks-rust-hi","licenses":[{"license":{"name":"Apache-2.0"}}],"type":"application"},{"version":"git-24.236.54363-d7cdf6a","name":"luci-i18n-shadowsocks-rust-hu","licenses":[{"license":{"name":"Apache-2.0"}}],"type":"application"},{"name":"luci-i18n-shadowsocks-rust-it","version":"git-24.236.54363-d7cdf6a","type":"application","licenses":[{"license":{"name":"Apache-2.0"}}]},{"version":"git-24.236.54363-d7cdf6a","name":"luci-i18n-shadowsocks-rust-ja","licenses":[{"license":{"name":"Apache-2.0"}}],"type":"application"},{"name":"luci-i18n-shadowsocks-rust-ko","version":"git-24.236.54363-d7cdf6a","type":"application","licenses":[{"license":{"name":"Apache-2.0"}}]},{"type":"application","licenses":[{"license":{"name":"Apache-2.0"}}],"name":"luci-i18n-shadowsocks-rust-lt","version":"git-24.236.54363-d7cdf6a"},{"licenses":[{"license":{"name":"Apache-2.0"}}],"type":"application","version":"git-24.236.54363-d7cdf6a","name":"luci-i18n-shadowsocks-rust-mr"},{"name":"luci-i18n-shadowsocks-rust-ms","version":"git-24.236.54363-d7cdf6a","type":"application","licenses":[{"license":{"name":"Apache-2.0"}}]},{"type":"application","licenses":[{"license":{"name":"Apache-2.0"}}],"name":"luci-i18n-shadowsocks-rust-nl","version":"git-24.236.54363-d7cdf6a"},{"licenses":[{"license":{"name":"Apache-2.0"}}],"type":"application","version":"git-24.236.54363-d7cdf6a","name":"luci-i18n-shadowsocks-rust-no"},{"licenses":[{"license":{"name":"Apache-2.0"}}],"type":"application","version":"git-24.236.54363-d7cdf6a","name":"luci-i18n-shadowsocks-rust-pl"},{"version":"git-24.236.54363-d7cdf6a","name":"luci-i18n-shadowsocks-rust-pt","licenses":[{"license":{"name":"Apache-2.0"}}],"type":"application"},{"version":"git-24.236.54363-d7cdf6a","name":"luci-i18n-shadowsocks-rust-pt-br","licenses":[{"license":{"name":"Apache-2.0"}}],"type":"application"},{"name":"luci-i18n-shadowsocks-rust-ro","version":"git-24.236.54363-d7cdf6a","type":"application","licenses":[{"license":{"name":"Apache-2.0"}}]},{"version":"git-24.236.54363-d7cdf6a","name":"luci-i18n-shadowsocks-rust-ru","licenses":[{"license":{"name":"Apache-2.0"}}],"type":"application"},{"version":"git-24.236.54363-d7cdf6a","name":"luci-i18n-shadowsocks-rust-sk","licenses":[{"license":{"name":"Apache-2.0"}}],"type":"application"},{"name":"luci-i18n-shadowsocks-rust-sv","version":"git-24.236.54363-d7cdf6a","type":"application","licenses":[{"license":{"name":"Apache-2.0"}}]},{"name":"luci-i18n-shadowsocks-rust-tr","version":"git-24.236.54363-d7cdf6a","type":"application","licenses":[{"license":{"name":"Apache-2.0"}}]},{"type":"application","licenses":[{"license":{"name":"Apache-2.0"}}],"name":"luci-i18n-shadowsocks-rust-uk","version":"git-24.236.54363-d7cdf6a"},{"type":"application","licenses":[{"license":{"name":"Apache-2.0"}}],"name":"luci-i18n-shadowsocks-rust-vi","version":"git-24.236.54363-d7cdf6a"},{"version":"git-24.236.54363-d7cdf6a","name":"luci-i18n-shadowsocks-rust-zh-cn","licenses":[{"license":{"name":"Apache-2.0"}}],"type":"application"},{"version":"git-24.236.54363-d7cdf6a","name":"luci-i18n-shadowsocks-rust-zh-tw","licenses":[{"license":{"name":"Apache-2.0"}}],"type":"application"},{"version":"1.21.2","name":"shadowsocks-rust-config","licenses":[{"license":{"name":"MIT"}}],"type":"application"},{"type":"application","licenses":[{"license":{"name":"MIT"}}],"name":"shadowsocks-rust-sslocal","version":"1.21.2"},{"licenses":[{"license":{"name":"MIT"}}],"type":"application","version":"1.21.2","name":"shadowsocks-rust-ssmanager"},{"licenses":[{"license":{"name":"MIT"}}],"type":"application","version":"1.21.2","name":"shadowsocks-rust-ssserver"},{"version":"1.21.2","name":"shadowsocks-rust-ssservice","licenses":[{"license":{"name":"MIT"}}],"type":"application"},{"type":"application","licenses":[{"license":{"name":"MIT"}}],"name":"shadowsocks-rust-ssurl","version":"1.21.2"}],"bomFormat":"CycloneDX","serialNumber":"urn:uuid:8bfc5dbd-0ad9-480a-b9d2-39836d13eded","metadata":{"timestamp":"2025-03-02T03:23:37Z"},"version":1}