{"components":[{"name":"einat-ebpf","version":"0.1.7","licenses":[{"license":{"name":"GPL-2.0-or-later"}},{"license":{"name":"GPL-2.0-only"}}],"type":"application"},{"name":"luci-app-shadowsocks-rust","version":"git-24.236.54363-d7cdf6a","type":"application","licenses":[{"license":{"name":"Apache-2.0"}}]},{"version":"git-24.236.54363-d7cdf6a","type":"application","licenses":[{"license":{"name":"Apache-2.0"}}],"name":"luci-i18n-shadowsocks-rust-ar"},{"licenses":[{"license":{"name":"Apache-2.0"}}],"type":"application","version":"git-24.236.54363-d7cdf6a","name":"luci-i18n-shadowsocks-rust-bg"},{"name":"luci-i18n-shadowsocks-rust-bn","version":"git-24.236.54363-d7cdf6a","licenses":[{"license":{"name":"Apache-2.0"}}],"type":"application"},{"licenses":[{"license":{"name":"Apache-2.0"}}],"type":"application","version":"git-24.236.54363-d7cdf6a","name":"luci-i18n-shadowsocks-rust-ca"},{"version":"git-24.236.54363-d7cdf6a","licenses":[{"license":{"name":"Apache-2.0"}}],"type":"application","name":"luci-i18n-shadowsocks-rust-cs"},{"name":"luci-i18n-shadowsocks-rust-da","version":"git-24.236.54363-d7cdf6a","type":"application","licenses":[{"license":{"name":"Apache-2.0"}}]},{"type":"application","licenses":[{"license":{"name":"Apache-2.0"}}],"version":"git-24.236.54363-d7cdf6a","name":"luci-i18n-shadowsocks-rust-de"},{"name":"luci-i18n-shadowsocks-rust-el","version":"git-24.236.54363-d7cdf6a","licenses":[{"license":{"name":"Apache-2.0"}}],"type":"application"},{"name":"luci-i18n-shadowsocks-rust-es","licenses":[{"license":{"name":"Apache-2.0"}}],"type":"application","version":"git-24.236.54363-d7cdf6a"},{"version":"git-24.236.54363-d7cdf6a","type":"application","licenses":[{"license":{"name":"Apache-2.0"}}],"name":"luci-i18n-shadowsocks-rust-fi"},{"version":"git-24.236.54363-d7cdf6a","licenses":[{"license":{"name":"Apache-2.0"}}],"type":"application","name":"luci-i18n-shadowsocks-rust-fr"},{"licenses":[{"license":{"name":"Apache-2.0"}}],"type":"application","version":"git-24.236.54363-d7cdf6a","name":"luci-i18n-shadowsocks-rust-he"},{"type":"application","licenses":[{"license":{"name":"Apache-2.0"}}],"version":"git-24.236.54363-d7cdf6a","name":"luci-i18n-shadowsocks-rust-hi"},{"type":"application","licenses":[{"license":{"name":"Apache-2.0"}}],"version":"git-24.236.54363-d7cdf6a","name":"luci-i18n-shadowsocks-rust-hu"},{"name":"luci-i18n-shadowsocks-rust-it","licenses":[{"license":{"name":"Apache-2.0"}}],"type":"application","version":"git-24.236.54363-d7cdf6a"},{"licenses":[{"license":{"name":"Apache-2.0"}}],"type":"application","version":"git-24.236.54363-d7cdf6a","name":"luci-i18n-shadowsocks-rust-ja"},{"version":"git-24.236.54363-d7cdf6a","type":"application","licenses":[{"license":{"name":"Apache-2.0"}}],"name":"luci-i18n-shadowsocks-rust-ko"},{"name":"luci-i18n-shadowsocks-rust-lt","licenses":[{"license":{"name":"Apache-2.0"}}],"type":"application","version":"git-24.236.54363-d7cdf6a"},{"version":"git-24.236.54363-d7cdf6a","type":"application","licenses":[{"license":{"name":"Apache-2.0"}}],"name":"luci-i18n-shadowsocks-rust-mr"},{"name":"luci-i18n-shadowsocks-rust-ms","version":"git-24.236.54363-d7cdf6a","licenses":[{"license":{"name":"Apache-2.0"}}],"type":"application"},{"name":"luci-i18n-shadowsocks-rust-nl","version":"git-24.236.54363-d7cdf6a","licenses":[{"license":{"name":"Apache-2.0"}}],"type":"application"},{"name":"luci-i18n-shadowsocks-rust-no","type":"application","licenses":[{"license":{"name":"Apache-2.0"}}],"version":"git-24.236.54363-d7cdf6a"},{"type":"application","licenses":[{"license":{"name":"Apache-2.0"}}],"version":"git-24.236.54363-d7cdf6a","name":"luci-i18n-shadowsocks-rust-pl"},{"name":"luci-i18n-shadowsocks-rust-pt","version":"git-24.236.54363-d7cdf6a","type":"application","licenses":[{"license":{"name":"Apache-2.0"}}]},{"type":"application","licenses":[{"license":{"name":"Apache-2.0"}}],"version":"git-24.236.54363-d7cdf6a","name":"luci-i18n-shadowsocks-rust-pt-br"},{"version":"git-24.236.54363-d7cdf6a","type":"application","licenses":[{"license":{"name":"Apache-2.0"}}],"name":"luci-i18n-shadowsocks-rust-ro"},{"name":"luci-i18n-shadowsocks-rust-ru","version":"git-24.236.54363-d7cdf6a","type":"application","licenses":[{"license":{"name":"Apache-2.0"}}]},{"version":"git-24.236.54363-d7cdf6a","licenses":[{"license":{"name":"Apache-2.0"}}],"type":"application","name":"luci-i18n-shadowsocks-rust-sk"},{"type":"application","licenses":[{"license":{"name":"Apache-2.0"}}],"version":"git-24.236.54363-d7cdf6a","name":"luci-i18n-shadowsocks-rust-sv"},{"licenses":[{"license":{"name":"Apache-2.0"}}],"type":"application","version":"git-24.236.54363-d7cdf6a","name":"luci-i18n-shadowsocks-rust-tr"},{"name":"luci-i18n-shadowsocks-rust-uk","licenses":[{"license":{"name":"Apache-2.0"}}],"type":"application","version":"git-24.236.54363-d7cdf6a"},{"version":"git-24.236.54363-d7cdf6a","licenses":[{"license":{"name":"Apache-2.0"}}],"type":"application","name":"luci-i18n-shadowsocks-rust-vi"},{"type":"application","licenses":[{"license":{"name":"Apache-2.0"}}],"version":"git-24.236.54363-d7cdf6a","name":"luci-i18n-shadowsocks-rust-zh-cn"},{"version":"git-24.236.54363-d7cdf6a","type":"application","licenses":[{"license":{"name":"Apache-2.0"}}],"name":"luci-i18n-shadowsocks-rust-zh-tw"},{"licenses":[{"license":{"name":"MIT"}}],"type":"application","version":"1.21.2","name":"shadowsocks-rust-config"},{"version":"1.21.2","licenses":[{"license":{"name":"MIT"}}],"type":"application","name":"shadowsocks-rust-sslocal"},{"type":"application","licenses":[{"license":{"name":"MIT"}}],"version":"1.21.2","name":"shadowsocks-rust-ssmanager"},{"name":"shadowsocks-rust-ssserver","licenses":[{"license":{"name":"MIT"}}],"type":"application","version":"1.21.2"},{"name":"shadowsocks-rust-ssservice","type":"application","licenses":[{"license":{"name":"MIT"}}],"version":"1.21.2"},{"type":"application","licenses":[{"license":{"name":"MIT"}}],"version":"1.21.2","name":"shadowsocks-rust-ssurl"}],"specVersion":"1.4","metadata":{"timestamp":"2025-03-24T12:13:17Z"},"bomFormat":"CycloneDX","version":1,"serialNumber":"urn:uuid:b8eaf201-be14-4188-b952-aa21c069902f"}